esi_utils_vectors/__init__.py
esi_utils_vectors/ecef.py
esi_utils_vectors/point.py
esi_utils_vectors/vector.py
esi_utils_vectors-1.0.3.dist-info/licenses/LICENSE.md
esi_utils_vectors-1.0.3.dist-info/METADATA
esi_utils_vectors-1.0.3.dist-info/WHEEL
esi_utils_vectors-1.0.3.dist-info/top_level.txt
esi_utils_vectors-1.0.3.dist-info/RECORD
