Metadata-Version: 2.4
Name: esi-utils-vectors
Version: 1.0.3
Summary: USGS Earthquake Impact Utilities for Vectors
Author-email: Mike Hearne <mhearne@usgs.gov>, Gabe Ferragut <gferragut@usgs.gov>
License: License
Requires-Python: >=3.11
License-File: LICENSE.md
Requires-Dist: esi-extern-openquake>=1.0.0
Requires-Dist: numpy>=1.26
Provides-Extra: dev
Requires-Dist: build>=0.7.0; extra == "dev"
Requires-Dist: black>=21; extra == "dev"
Requires-Dist: flake8>=3.9; extra == "dev"
Requires-Dist: ipython>=7.26; extra == "dev"
Provides-Extra: test
Requires-Dist: pytest>=6.2; extra == "test"
Requires-Dist: pytest-cov>=2.12; extra == "test"
Requires-Dist: pytest-console-scripts>=1.2; extra == "test"
Provides-Extra: build
Requires-Dist: build; extra == "build"
Requires-Dist: packaging>=24.2; extra == "build"
Requires-Dist: twine; extra == "build"
Requires-Dist: check-wheel-contents; extra == "build"
Dynamic: license-file
